reliably_cli-0.28.1.dist-info/METADATA
reliably_cli-0.28.1.dist-info/WHEEL
reliably_cli-0.28.1.dist-info/entry_points.txt
reliably_cli-0.28.1.dist-info/licenses/LICENSE
reliably_cli/__init__.py
reliably_cli/__main__.py
reliably_cli/__version__.py
reliably_cli/agent/__init__.py
reliably_cli/agent/cli.py
reliably_cli/agent/plan/__init__.py
reliably_cli/agent/plan/providers/__init__.py
reliably_cli/agent/plan/providers/github.py
reliably_cli/client.py
reliably_cli/config/__init__.py
reliably_cli/config/cli.py
reliably_cli/config/types.py
reliably_cli/format.py
reliably_cli/library/__init__.py
reliably_cli/library/cli.py
reliably_cli/library/starters.py
reliably_cli/log.py
reliably_cli/services/__init__.py
reliably_cli/services/cli.py
reliably_cli/services/org.py
reliably_cli/services/plan.py
reliably_cli/types.py
reliably_cli-0.28.1.dist-info/RECORD
