Metadata-Version: 2.1
Name: reliably-cli
Version: 0.28.1
Summary: Reliably CLI
Author-Email: Sylvain Hellegouarch <sylvain@reliably.com>
License: Apache-2.0
Classifier: License :: OSI Approved :: Apache Software License
Classifier: Development Status :: 5 - Production/Stable
Classifier: Operating System :: OS Independent
Classifier: Programming Language :: Python :: 3
Classifier: Programming Language :: Python :: 3.10
Classifier: Programming Language :: Python :: 3.11
Classifier: Programming Language :: Python :: 3.12
Classifier: Topic :: System :: Monitoring
Classifier: Topic :: Utilities
Project-URL: Homepage, https://reliably.com/
Project-URL: Repository, https://github.com/reliablyhq/cli
Project-URL: Documentation, https://reliably.com/docs/cli/
Project-URL: Changelog, https://github.com/reliablyhq/cli/blob/main/CHANGELOG.md
Requires-Python: >=3.10
Requires-Dist: httpx[http2]>=0.23.0
Requires-Dist: pydantic>=2.0
Requires-Dist: typer>=0.6.1
Requires-Dist: anyio[trio]>=3.6.2
Requires-Dist: tomli>=1.1.0; python_version < "3.11"
Requires-Dist: ruamel.yaml>=0.17.21
Requires-Dist: rich>=13.3.1
Requires-Dist: chaostoolkit-addons>=0.4.0
Requires-Dist: chaostoolkit>=1.19.0
Requires-Dist: chaostoolkit-lib>=1.42.0
Requires-Dist: chaostoolkit-reliably>=0.22.0
Requires-Dist: orjson>=3.8.10
Requires-Dist: pydantic-settings>=2.0.0
Requires-Dist: pyoxidizer>=0.22.0; extra == "bin-builder"
Requires-Dist: chaostoolkit-aws>=0.21.3; extra == "chaostoolkit"
Requires-Dist: chaostoolkit-kubernetes>=0.26.4; extra == "chaostoolkit"
Requires-Dist: chaostoolkit-google-cloud-platform>=0.8.2; extra == "chaostoolkit"
Requires-Dist: chaostoolkit-prometheus>=0.5.0; extra == "chaostoolkit"
Requires-Dist: chaostoolkit-opentracing>=0.9.1; extra == "chaostoolkit"
Requires-Dist: chaostoolkit-dynatrace>=0.2.0; extra == "chaostoolkit"
Requires-Dist: chaostoolkit-grafana>=0.2.0; extra == "chaostoolkit"
Requires-Dist: chaostoolkit-slack>=0.5.7; extra == "chaostoolkit"
Requires-Dist: chaostoolkit-datadog>=0.1.1; extra == "chaostoolkit"
Requires-Dist: jsonpath2>=0.4.5; extra == "chaostoolkit"
Provides-Extra: bin-builder
Provides-Extra: chaostoolkit
